  
{
  "Studentai": [
    {
      "Vardas": "Petras",
      "Pavarde": "Petraitis",
      "Mokosi": "KTU Informatikos fakultete III kurse",
      "Islaikes": [
        {
          "Modulis": "Informatika",
          "Balas": "9"
        },
        {
          "Modulis": "Filosofija"
        },
        {
          "Modulis": "Imitacinis modeliavimas",
          "Balas": "8"
        }
      ]
    },
    {
      "Vardas": "Pranas",
      "Pavarde": "Petraitis",
      "Mokosi": "VDU Gamtos moksl킬 fakulteto II kurse",
      "Islaikes": [
        {
          "Modulis": "Informatika",
          "Balas": "5"
        },
        {
          "Modulis": "Filosofija",
          "Balas": "9"
        },
        {
          "Modulis": "Lotyn킬 kalba",
          "Balas": "5"
        }
      ]
    },
{
      "Vardas": "Petras",
      "Pavarde": "Petraitis",
      "Mokosi": "KTU Statybos ir architekt큰ros fakultete IV kurse",
      "Islaikes": [
        {
          "Modulis": "Informatika",
          "Balas": "7"
        },
        {
          "Modulis": "Filosofija"
        },
        {
          "Modulis": "Brai탑yba",
          "Balas": "8"
        }
      ]
    }
  ]
}